ec2api/__init__.py
ec2api/clients.py
ec2api/config.py
ec2api/context.py
ec2api/exception.py
ec2api/i18n.py
ec2api/opts.py
ec2api/paths.py
ec2api/service.py
ec2api/utils.py
ec2api/version.py
ec2api/wsgi.py
ec2api/api/__init__.py
ec2api/api/address.py
ec2api/api/apirequest.py
ec2api/api/auth.py
ec2api/api/availability_zone.py
ec2api/api/cloud.py
ec2api/api/common.py
ec2api/api/customer_gateway.py
ec2api/api/dhcp_options.py
ec2api/api/ec2utils.py
ec2api/api/faults.py
ec2api/api/image.py
ec2api/api/instance.py
ec2api/api/internet_gateway.py
ec2api/api/key_pair.py
ec2api/api/network_interface.py
ec2api/api/opts.py
ec2api/api/route_table.py
ec2api/api/security_group.py
ec2api/api/snapshot.py
ec2api/api/subnet.py
ec2api/api/tag.py
ec2api/api/validator.py
ec2api/api/volume.py
ec2api/api/vpc.py
ec2api/api/vpn_connection.py
ec2api/api/vpn_gateway.py
ec2api/cmd/__init__.py
ec2api/cmd/api.py
ec2api/cmd/api_metadata.py
ec2api/cmd/api_s3.py
ec2api/cmd/manage.py
ec2api/db/__init__.py
ec2api/db/api.py
ec2api/db/migration.py
ec2api/db/sqlalchemy/__init__.py
ec2api/db/sqlalchemy/api.py
ec2api/db/sqlalchemy/migration.py
ec2api/db/sqlalchemy/models.py
ec2api/db/sqlalchemy/migrate_repo/README
ec2api/db/sqlalchemy/migrate_repo/__init__.py
ec2api/db/sqlalchemy/migrate_repo/manage.py
ec2api/db/sqlalchemy/migrate_repo/migrate.cfg
ec2api/db/sqlalchemy/migrate_repo/versions/001_juno.py
ec2api/db/sqlalchemy/migrate_repo/versions/__init__.py
ec2api/hacking/__init__.py
ec2api/hacking/checks.py
ec2api/metadata/__init__.py
ec2api/metadata/api.py
ec2api/metadata/opts.py
ec2api/s3/__init__.py
ec2api/s3/opts.py
ec2api/s3/s3server.py
ec2api/tests/__init__.py
ec2api/tests/botocoreclient.py
ec2api/tests/unit/__init__.py
ec2api/tests/unit/abs.tar.gz
ec2api/tests/unit/base.py
ec2api/tests/unit/fakes.py
ec2api/tests/unit/fakes_request_response.py
ec2api/tests/unit/matchers.py
ec2api/tests/unit/rel.tar.gz
ec2api/tests/unit/test_address.py
ec2api/tests/unit/test_api_init.py
ec2_api-17.0.0.dist-info/AUTHORS
ec2_api-17.0.0.dist-info/LICENSE
ec2_api-17.0.0.dist-info/METADATA
ec2_api-17.0.0.dist-info/WHEEL
ec2_api-17.0.0.dist-info/entry_points.txt
ec2_api-17.0.0.dist-info/pbr.json
ec2_api-17.0.0.dist-info/top_level.txt
ec2_api-17.0.0.dist-info/RECORD
