Metadata-Version: 2.1
Name: ec2-api
Version: 17.0.0
Summary: OpenStack Ec2api Service
Home-page: https://launchpad.net/ec2-api
Author: OpenStack
Author-email: openstack-discuss@lists.openstack.org
License: Apache License, Version 2.0
Platform: UNKNOWN
Classifier: Environment :: OpenStack
Classifier: Intended Audience :: Information Technology
Classifier: Intended Audience :: System Administrators
Classifier: License :: OSI Approved :: Apache Software License
Classifier: Operating System :: POSIX :: Linux
Classifier: Programming Language :: Python
Classifier: Programming Language :: Python :: 3
Classifier: Programming Language :: Python :: 3.6
Classifier: Programming Language :: Python :: 3.7
Classifier: Programming Language :: Python :: 3.8
Classifier: Programming Language :: Python :: 3.9
Requires-Dist: Paste (>=2.0.3)
Requires-Dist: PasteDeploy (>=1.5.2)
Requires-Dist: Routes (>=2.4.1)
Requires-Dist: SQLAlchemy (>=1.2.5)
Requires-Dist: WebOb (>=1.7.4)
Requires-Dist: botocore (>=1.9.7)
Requires-Dist: cryptography (>=2.1.4)
Requires-Dist: eventlet (>=0.20.0)
Requires-Dist: greenlet (>=0.4.13)
Requires-Dist: httplib2 (>=0.10.3)
Requires-Dist: keystoneauth1 (>=3.14.0)
Requires-Dist: lxml (>=4.1.1)
Requires-Dist: oslo.cache (>=1.29.0)
Requires-Dist: oslo.concurrency (>=3.26.0)
Requires-Dist: oslo.config (>=5.2.0)
Requires-Dist: oslo.context (>=2.20.0)
Requires-Dist: oslo.db (>=4.40.0)
Requires-Dist: oslo.log (>=3.37.0)
Requires-Dist: oslo.serialization (>=2.25.0)
Requires-Dist: oslo.service (>=1.30.0)
Requires-Dist: oslo.utils (>=3.36.0)
Requires-Dist: pbr (>=3.1.1)
Requires-Dist: python-cinderclient (>=3.5.0)
Requires-Dist: python-glanceclient (>=2.16.0)
Requires-Dist: python-keystoneclient (>=3.15.0)
Requires-Dist: python-neutronclient (>=6.7.0)
Requires-Dist: python-novaclient (>=10.1.0)
Requires-Dist: python-openstackclient (>=3.14.0)
Requires-Dist: sqlalchemy-migrate (>=0.11.0)
